iq_sim/__init__.py
iq_sim/iq_sim.py
python_iq_sim-0.0.4.dist-info/LICENSE
python_iq_sim-0.0.4.dist-info/METADATA
python_iq_sim-0.0.4.dist-info/WHEEL
python_iq_sim-0.0.4.dist-info/top_level.txt
python_iq_sim-0.0.4.dist-info/RECORD
