Metadata-Version: 2.1
Name: python-iq-sim
Version: 0.0.4
Summary: Python Library for starting and managing simulations in the Intelligent Quads Cloud
Home-page: UNKNOWN
Author: Eric Johnson
Author-email: 
License: UNKNOWN
Keywords: python,sim,cloud,mavlink,ardupilot,px4
Platform: UNKNOWN
Classifier: Development Status :: 1 - Planning
Classifier: Intended Audience :: Developers
Classifier: Programming Language :: Python :: 3
Classifier: Operating System :: Unix
Classifier: Operating System :: MacOS :: MacOS X
Classifier: Operating System :: Microsoft :: Windows
